src/PRNG.vhd
LIBRARY ieee;
USE ieee.std_logic_1164.ALL;
use IEEE.numeric_std.all;

ENTITY prng IS
  PORT (clk, rst,gen: IN std_logic;
        output: OUT std_logic_vector (13 DOWNTO 0));
END prng;

ARCHITECTURE rtl OF prng IS
  SIGNAL currstate, nextstate: std_logic_vector (13 DOWNTO 0);
  signal min : std_logic_vector(13 downto 0) := "00000001111111";
  signal max : std_logic_vector(13 downto 0) := "11111110000000";

  SIGNAL feedback: std_logic;
BEGIN

  StateReg: PROCESS (clk,Rst)
  BEGIN
    IF (rst = '1') THEN
      currstate <= (0 => '1', OTHERS =>'0');
    ELSIF rising_edge(clk) and gen = '1' THEN
        currstate <= nextstate;  
    END IF;
  END PROCESS;

  process(clk)
  begin
    if(currstate < min) then
      output <= min;
    elsif currstate > max then
      output <= max;
    else
      output <= currstate;
    end if;
  end process;    
      
  
  feedback <= currstate(13) XOR currstate(4) XOR currstate(2) XOR currstate(0);
  nextstate <= feedback & currstate(13 DOWNTO 1);

  end rtl;

src/prng_tb.vhd
library ieee;
use ieee.std_logic_1164.all;
use ieee.numeric_std.all;

entity prng_tb is
end prng_tb;

architecture tb of prng_tb is
    constant CLK_PERIOD : time := 500 ns;
    signal clk : std_logic := '0';
    signal rst : std_logic := '0';
    signal gen : std_logic := '0';
    signal prn : std_logic_vector (13 downto 0);
    

    component prng
        port (
            clk, rst,gen: IN std_logic;
            output: OUT std_logic_vector (13 DOWNTO 0)
        );
    end component;

begin
    prng_inst : prng
        port map (
            clk => clk,
            rst => rst,
            gen => gen,
            output => prn
        );

        clk <= not clk after CLK_PERIOD/2;
        gen <= not gen after CLK_PERIOD/2;
        process begin
            rst <= '1';
            wait for 510 ns;
            rst <= '0';
            wait;
        end process;
end tb;

src/prng.vcd
$date
  Mon May 31 20:58:56 2021
$end
$version
  GHDL v0
$end
$timescale
  1 fs
$end
$scope module standard $end
$upscope $end
$scope module std_logic_1164 $end
$upscope $end
$scope module numeric_std $end
$upscope $end
$scope module prng_tb $end
$var reg 1 ! clk $end
$var reg 1 " rst $end
$var reg 1 # gen $end
$var reg 14 $ prn[13:0] $end
$scope module prng_inst $end
$var reg 1 % clk $end
$var reg 1 & rst $end
$var reg 1 ' gen $end
$var reg 14 ( output[13:0] $end
$var reg 14 ) currstate[13:0] $end
$var reg 14 * nextstate[13:0] $end
$var reg 14 + min[13:0] $end
$var reg 14 , max[13:0] $end
$var reg 1 - feedback $end
$upscope $end
$upscope $end
$enddefinitions $end
#0
0!
1"
0#
b00000001111111 $
0%
1&
0'
b00000001111111 (
b00000000000001 )
b10000000000000 *
b00000001111111 +
b11111110000000 ,
1-
#250000000
1!
1#
1%
1'
#500000000
0!
0#
0%
0'
#510000000
0"
0&
#750000000
1!
1#
1%
1'
b10000000000000 )
b11000000000000 *
#1000000000
0!
0#
b10000000000000 $
0%
0'
b10000000000000 (
#1250000000
1!
1#
1%
1'
b11000000000000 )
b11100000000000 *
#1500000000
0!
0#
b11000000000000 $
0%
0'
b11000000000000 (
#1750000000
1!
1#
1%
1'
b11100000000000 )
b11110000000000 *
#2000000000
0!
0#
b11100000000000 $
0%
0'
b11100000000000 (
#2250000000
1!
1#
1%
1'
b11110000000000 )
b11111000000000 *
#2500000000
0!
0#
b11110000000000 $
0%
0'
b11110000000000 (
#2750000000
1!
1#
1%
1'
b11111000000000 )
b11111100000000 *
#3000000000
0!
0#
b11111000000000 $
0%
0'
b11111000000000 (
#3250000000
1!
1#
1%
1'
b11111100000000 )
b11111110000000 *
#3500000000
0!
0#
b11111100000000 $
0%
0'
b11111100000000 (
#3750000000
1!
1#
1%
1'
b11111110000000 )
b11111111000000 *
#4000000000
0!
0#
b11111110000000 $
0%
0'
b11111110000000 (
#4250000000
1!
1#
1%
1'
b11111111000000 )
b11111111100000 *
#4500000000
0!
0#
0%
0'
#4750000000
1!
1#
1%
1'
b11111111100000 )
b11111111110000 *
#5000000000
0!
0#
0%
0'
#5250000000
1!
1#
1%
1'
b11111111110000 )
b01111111111000 *
0-
#5500000000
0!
0#
0%
0'
#5750000000
1!
1#
1%
1'
b01111111111000 )
b10111111111100 *
1-
#6000000000
0!
0#
b01111111111000 $
0%
0'
b01111111111000 (
#6250000000
1!
1#
1%
1'
b10111111111100 )
b11011111111110 *
#6500000000
0!
0#
b10111111111100 $
0%
0'
b10111111111100 (
#6750000000
1!
1#
1%
1'
b11011111111110 )
b11101111111111 *
#7000000000
0!
0#
b11011111111110 $
0%
0'
b11011111111110 (
#7250000000
1!
1#
1%
1'
b11101111111111 )
b01110111111111 *
0-
#7500000000
0!
0#
b11101111111111 $
0%
0'
b11101111111111 (
#7750000000
1!
1#
1%
1'
b01110111111111 )
b10111011111111 *
1-
#8000000000
0!
0#
b01110111111111 $
0%
0'
b01110111111111 (
#8250000000
1!
1#
1%
1'
b10111011111111 )
b01011101111111 *
0-
#8500000000
0!
0#
b10111011111111 $
0%
0'
b10111011111111 (
#8750000000
1!
1#
1%
1'
b01011101111111 )
b10101110111111 *
1-
#9000000000
0!
0#
b01011101111111 $
0%
0'
b01011101111111 (
#9250000000
1!
1#
1%
1'
b10101110111111 )
b01010111011111 *
0-
#9500000000
0!
0#
b10101110111111 $
0%
0'
b10101110111111 (
#9750000000
1!
1#
1%
1'
b01010111011111 )
b10101011101111 *
1-
#10000000000
0!
0#
b01010111011111 $
0%
0'
b01010111011111 (
#10250000000
1!
1#
1%
1'
b10101011101111 )
b11010101110111 *
#10500000000
0!
0#
b10101011101111 $
0%
0'
b10101011101111 (
#10750000000
1!
1#
1%
1'
b11010101110111 )
b01101010111011 *
0-
#11000000000
0!
0#
b11010101110111 $
0%
0'
b11010101110111 (
#11250000000
1!
1#
1%
1'
b01101010111011 )
b00110101011101 *
#11500000000
0!
0#
b01101010111011 $
0%
0'
b01101010111011 (
#11750000000
1!
1#
1%
1'
b00110101011101 )
b10011010101110 *
1-
#12000000000
0!
0#
b00110101011101 $
0%
0'
b00110101011101 (
#12250000000
1!
1#
1%
1'
b10011010101110 )
b01001101010111 *
0-
#12500000000
0!
0#
b10011010101110 $
0%
0'
b10011010101110 (
#12750000000
1!
1#
1%
1'
b01001101010111 )
b10100110101011 *
1-
#13000000000
0!
0#
b01001101010111 $
0%
0'
b01001101010111 (
#13250000000
1!
1#
1%
1'
b10100110101011 )
b01010011010101 *
0-
#13500000000
0!
0#
b10100110101011 $
0%
0'
b10100110101011 (
#13750000000
1!
1#
1%
1'
b01010011010101 )
b10101001101010 *
1-
#14000000000
0!
0#
b01010011010101 $
0%
0'
b01010011010101 (
#14250000000
1!
1#
1%
1'
b10101001101010 )
b11010100110101 *
#14500000000
0!
0#
b10101001101010 $
0%
0'
b10101001101010 (
#14750000000
1!
1#
1%
1'
b11010100110101 )
b01101010011010 *
0-
#15000000000
0!
0#
b11010100110101 $
0%
0'
b11010100110101 (
#15250000000
1!
1#
1%
1'
b01101010011010 )
b10110101001101 *
1-
#15500000000
0!
0#
b01101010011010 $
0%
0'
b01101010011010 (
#15750000000
1!
1#
1%
1'
b10110101001101 )
b11011010100110 *
#16000000000
0!
0#
b10110101001101 $
0%
0'
b10110101001101 (
#16250000000
1!
1#
1%
1'
b11011010100110 )
b01101101010011 *
0-
#16500000000
0!
0#
b11011010100110 $
0%
0'
b11011010100110 (
#16750000000
1!
1#
1%
1'
b01101101010011 )
b00110110101001 *
#17000000000
0!
0#
b01101101010011 $
0%
0'
b01101101010011 (
#17250000000
1!
1#
1%
1'
b00110110101001 )
b10011011010100 *
1-
#17500000000
0!
0#
b00110110101001 $
0%
0'
b00110110101001 (
#17750000000
1!
1#
1%
1'
b10011011010100 )
b11001101101010 *
#18000000000
0!
0#
b10011011010100 $
0%
0'
b10011011010100 (
#18250000000
1!
1#
1%
1'
b11001101101010 )
b11100110110101 *
#18500000000
0!
0#
b11001101101010 $
0%
0'
b11001101101010 (
#18750000000
1!
1#
1%
1'
b11100110110101 )
b01110011011010 *
0-
#19000000000
0!
0#
b11100110110101 $
0%
0'
b11100110110101 (
#19250000000
1!
1#
1%
1'
b01110011011010 )
b10111001101101 *
1-
#19500000000
0!
0#
b01110011011010 $
0%
0'
b01110011011010 (
#19750000000
1!
1#
1%
1'
b10111001101101 )
b11011100110110 *
#20000000000
0!
0#
b10111001101101 $
0%
0'
b10111001101101 (
#20250000000
1!
1#
1%
1'
b11011100110110 )
b11101110011011 *
#20500000000
0!
0#
b11011100110110 $
0%
0'
b11011100110110 (
#20750000000
1!
1#
1%
1'
b11101110011011 )
b11110111001101 *
#21000000000
0!
0#
b11101110011011 $
0%
0'
b11101110011011 (
#21250000000
1!
1#
1%
1'
b11110111001101 )
b11111011100110 *
#21500000000
0!
0#
b11110111001101 $
0%
0'
b11110111001101 (
#21750000000
1!
1#
1%
1'
b11111011100110 )
b01111101110011 *
0-
#22000000000
0!
0#
b11111011100110 $
0%
0'
b11111011100110 (
#22250000000
1!
1#
1%
1'
b01111101110011 )
b00111110111001 *
#22500000000
0!
0#
b01111101110011 $
0%
0'
b01111101110011 (
#22750000000
1!
1#
1%
1'
b00111110111001 )
b00011111011100 *
#23000000000
0!
0#
b00111110111001 $
0%
0'
b00111110111001 (
#23250000000
1!
1#
1%
1'
b00011111011100 )
b00001111101110 *
#23500000000
0!
0#
b00011111011100 $
0%
0'
b00011111011100 (
#23750000000
1!
1#
1%
1'
b00001111101110 )
b10000111110111 *
1-
#24000000000
0!
0#
b00001111101110 $
0%
0'
b00001111101110 (
#24250000000
1!
1#
1%
1'
b10000111110111 )
b01000011111011 *
0-
#24500000000
0!
0#
b10000111110111 $
0%
0'
b10000111110111 (
#24750000000
1!
1#
1%
1'
b01000011111011 )
b00100001111101 *
#25000000000
0!
0#
b01000011111011 $
0%
0'
b01000011111011 (
#25250000000
1!
1#
1%
1'
b00100001111101 )
b10010000111110 *
1-
#25500000000
0!
0#
b00100001111101 $
0%
0'
b00100001111101 (
#25750000000
1!
1#
1%
1'
b10010000111110 )
b11001000011111 *
#26000000000
0!
0#
b10010000111110 $
0%
0'
b10010000111110 (
#26250000000
1!
1#
1%
1'
b11001000011111 )
b01100100001111 *
0-
#26500000000
0!
0#
b11001000011111 $
0%
0'
b11001000011111 (
#26750000000
1!
1#
1%
1'
b01100100001111 )
b00110010000111 *
#27000000000
0!
0#
b01100100001111 $
0%
0'
b01100100001111 (
#27250000000
1!
1#
1%
1'
b00110010000111 )
b00011001000011 *
#27500000000
0!
0#
b00110010000111 $
0%
0'
b00110010000111 (
#27750000000
1!
1#
1%
1'
b00011001000011 )
b10001100100001 *
1-
#28000000000
0!
0#
b00011001000011 $
0%
0'
b00011001000011 (
#28250000000
1!
1#
1%
1'
b10001100100001 )
b01000110010000 *
0-
#28500000000
0!
0#
b10001100100001 $
0%
0'
b10001100100001 (
#28750000000
1!
1#
1%
1'
b01000110010000 )
b10100011001000 *
1-
#29000000000
0!
0#
b01000110010000 $
0%
0'
b01000110010000 (
#29250000000
1!
1#
1%
1'
b10100011001000 )
b11010001100100 *
#29500000000
0!
0#
b10100011001000 $
0%
0'
b10100011001000 (
#29750000000
1!
1#
1%
1'
b11010001100100 )
b01101000110010 *
0-
#30000000000
0!
0#
b11010001100100 $
0%
0'
b11010001100100 (
#30250000000
1!
1#
1%
1'
b01101000110010 )
b10110100011001 *
1-
#30500000000
0!
0#
b01101000110010 $
0%
0'
b01101000110010 (
#30750000000
1!
1#
1%
1'
b10110100011001 )
b11011010001100 *
#31000000000
0!
0#
b10110100011001 $
0%
0'
b10110100011001 (
#31250000000
1!
1#
1%
1'
b11011010001100 )
b01101101000110 *
0-
#31500000000
0!
0#
b11011010001100 $
0%
0'
b11011010001100 (
#31750000000
1!
1#
1%
1'
b01101101000110 )
b10110110100011 *
1-
#32000000000
0!
0#
b01101101000110 $
0%
0'
b01101101000110 (
#32250000000
1!
1#
1%
1'
b10110110100011 )
b01011011010001 *
0-
#32500000000
0!
0#
b10110110100011 $
0%
0'
b10110110100011 (
#32750000000
1!
1#
1%
1'
b01011011010001 )
b00101101101000 *
#33000000000
0!
0#
b01011011010001 $
0%
0'
b01011011010001 (
#33250000000
1!
1#
1%
1'
b00101101101000 )
b00010110110100 *
#33500000000
0!
0#
b00101101101000 $
0%
0'
b00101101101000 (
#33750000000
1!
1#
1%
1'
b00010110110100 )
b00001011011010 *
#34000000000
0!
0#
b00010110110100 $
0%
0'
b00010110110100 (
#34250000000
1!
1#
1%
1'
b00001011011010 )
b10000101101101 *
1-
#34500000000
0!
0#
b00001011011010 $
0%
0'
b00001011011010 (
#34750000000
1!
1#
1%
1'
b10000101101101 )
b11000010110110 *
#35000000000
0!
0#
b10000101101101 $
0%
0'
b10000101101101 (
#35250000000
1!
1#
1%
1'
b11000010110110 )
b11100001011011 *
#35500000000
0!
0#
b11000010110110 $
0%
0'
b11000010110110 (
#35750000000
1!
1#
1%
1'
b11100001011011 )
b11110000101101 *
#36000000000
0!
0#
b11100001011011 $
0%
0'
b11100001011011 (
#36250000000
1!
1#
1%
1'
b11110000101101 )
b11111000010110 *
#36500000000
0!
0#
b11110000101101 $
0%
0'
b11110000101101 (
#36750000000
1!
1#
1%
1'
b11111000010110 )
b11111100001011 *
#37000000000
0!
0#
b11111000010110 $
0%
0'
b11111000010110 (
#37250000000
1!
1#
1%
1'
b11111100001011 )
b01111110000101 *
0-
#37500000000
0!
0#
b11111100001011 $
0%
0'
b11111100001011 (
#37750000000
1!
1#
1%
1'
b01111110000101 )
b00111111000010 *
#38000000000
0!
0#
b01111110000101 $
0%
0'
b01111110000101 (
#38250000000
1!
1#
1%
1'
b00111111000010 )
b00011111100001 *
#38500000000
0!
0#
b00111111000010 $
0%
0'
b00111111000010 (
#38750000000
1!
1#
1%
1'
b00011111100001 )
b10001111110000 *
1-
#39000000000
0!
0#
b00011111100001 $
0%
0'
b00011111100001 (
#39250000000
1!
1#
1%
1'
b10001111110000 )
b01000111111000 *
0-
#39500000000
0!
0#
b10001111110000 $
0%
0'
b10001111110000 (
#39750000000
1!
1#
1%
1'
b01000111111000 )
b10100011111100 *
1-
#40000000000
0!
0#
b01000111111000 $
0%
0'
b01000111111000 (
#40250000000
1!
1#
1%
1'
b10100011111100 )
b11010001111110 *
#40500000000
0!
0#
b10100011111100 $
0%
0'
b10100011111100 (
#40750000000
1!
1#
1%
1'
b11010001111110 )
b11101000111111 *
#41000000000
0!
0#
b11010001111110 $
0%
0'
b11010001111110 (
#41250000000
1!
1#
1%
1'
b11101000111111 )
b01110100011111 *
0-
#41500000000
0!
0#
b11101000111111 $
0%
0'
b11101000111111 (
#41750000000
1!
1#
1%
1'
b01110100011111 )
b10111010001111 *
1-
#42000000000
0!
0#
b01110100011111 $
0%
0'
b01110100011111 (
#42250000000
1!
1#
1%
1'
b10111010001111 )
b11011101000111 *
#42500000000
0!
0#
b10111010001111 $
0%
0'
b10111010001111 (
#42750000000
1!
1#
1%
1'
b11011101000111 )
b11101110100011 *
#43000000000
0!
0#
b11011101000111 $
0%
0'
b11011101000111 (
#43250000000
1!
1#
1%
1'
b11101110100011 )
b01110111010001 *
0-
#43500000000
0!
0#
b11101110100011 $
0%
0'
b11101110100011 (
#43750000000
1!
1#
1%
1'
b01110111010001 )
b00111011101000 *
#44000000000
0!
0#
b01110111010001 $
0%
0'
b01110111010001 (
#44250000000
1!
1#
1%
1'
b00111011101000 )
b00011101110100 *
#44500000000
0!
0#
b00111011101000 $
0%
0'
b00111011101000 (
#44750000000
1!
1#
1%
1'
b00011101110100 )
b00001110111010 *
#45000000000
0!
0#
b00011101110100 $
0%
0'
b00011101110100 (
#45250000000
1!
1#
1%
1'
b00001110111010 )
b10000111011101 *
1-
#45500000000
0!
0#
b00001110111010 $
0%
0'
b00001110111010 (
#45750000000
1!
1#
1%
1'
b10000111011101 )
b01000011101110 *
0-
#46000000000
0!
0#
b10000111011101 $
0%
0'
b10000111011101 (
#46250000000
1!
1#
1%
1'
b01000011101110 )
b10100001110111 *
1-
#46500000000
0!
0#
b01000011101110 $
0%
0'
b01000011101110 (
#46750000000
1!
1#
1%
1'
b10100001110111 )
b01010000111011 *
0-
#47000000000
0!
0#
b10100001110111 $
0%
0'
b10100001110111 (
#47250000000
1!
1#
1%
1'
b01010000111011 )
b00101000011101 *
#47500000000
0!
0#
b01010000111011 $
0%
0'
b01010000111011 (
#47750000000
1!
1#
1%
1'
b00101000011101 )
b10010100001110 *
1-
#48000000000
0!
0#
b00101000011101 $
0%
0'
b00101000011101 (
#48250000000
1!
1#
1%
1'
b10010100001110 )
b01001010000111 *
0-
#48500000000
0!
0#
b10010100001110 $
0%
0'
b10010100001110 (
#48750000000
1!
1#
1%
1'
b01001010000111 )
b00100101000011 *
#49000000000
0!
0#
b01001010000111 $
0%
0'
b01001010000111 (
#49250000000
1!
1#
1%
1'
b00100101000011 )
b10010010100001 *
1-
#49500000000
0!
0#
b00100101000011 $
0%
0'
b00100101000011 (
#49750000000
1!
1#
1%
1'
b10010010100001 )
b01001001010000 *
0-
#50000000000
0!
0#
b10010010100001 $
0%
0'
b10010010100001 (
#50250000000
1!
1#
1%
1'
b01001001010000 )
b10100100101000 *
1-
#50500000000
0!
0#
b01001001010000 $
0%
0'
b01001001010000 (
#50750000000
1!
1#
1%
1'
b10100100101000 )
b11010010010100 *
#51000000000
0!
0#
b10100100101000 $
0%
0'
b10100100101000 (
#51250000000
1!
1#
1%
1'
b11010010010100 )
b11101001001010 *
#51500000000
0!
0#
b11010010010100 $
0%
0'
b11010010010100 (
#51750000000
1!
1#
1%
1'
b11101001001010 )
b11110100100101 *
#52000000000
0!
0#
b11101001001010 $
0%
0'
b11101001001010 (
#52250000000
1!
1#
1%
1'
b11110100100101 )
b11111010010010 *
#52500000000
0!
0#
b11110100100101 $
0%
0'
b11110100100101 (
#52750000000
1!
1#
1%
1'
b11111010010010 )
b01111101001001 *
0-
#53000000000
0!
0#
b11111010010010 $
0%
0'
b11111010010010 (
#53250000000
1!
1#
1%
1'
b01111101001001 )
b10111110100100 *
1-
#53500000000
0!
0#
b01111101001001 $
0%
0'
b01111101001001 (
#53750000000
1!
1#
1%
1'
b10111110100100 )
b01011111010010 *
0-
#54000000000
0!
0#
b10111110100100 $
0%
0'
b10111110100100 (
#54250000000
1!
1#
1%
1'
b01011111010010 )
b10101111101001 *
1-
#54500000000
0!
0#
b01011111010010 $
0%
0'
b01011111010010 (
#54750000000
1!
1#
1%
1'
b10101111101001 )
b01010111110100 *
0-
#55000000000
0!
0#
b10101111101001 $
0%
0'
b10101111101001 (
#55250000000
1!
1#
1%
1'
b01010111110100 )
b00101011111010 *
#55500000000
0!
0#
b01010111110100 $
0%
0'
b01010111110100 (
#55750000000
1!
1#
1%
1'
b00101011111010 )
b10010101111101 *
1-
#56000000000
0!
0#
b00101011111010 $
0%
0'
b00101011111010 (
#56250000000
1!
1#
1%
1'
b10010101111101 )
b01001010111110 *
0-
#56500000000
0!
0#
b10010101111101 $
0%
0'
b10010101111101 (
#56750000000
1!
1#
1%
1'
b01001010111110 )
b00100101011111 *
#57000000000
0!
0#
b01001010111110 $
0%
0'
b01001010111110 (
#57250000000
1!
1#
1%
1'
b00100101011111 )
b10010010101111 *
1-
#57500000000
0!
0#
b00100101011111 $
0%
0'
b00100101011111 (
#57750000000
1!
1#
1%
1'
b10010010101111 )
b11001001010111 *
#58000000000
0!
0#
b10010010101111 $
0%
0'
b10010010101111 (
#58250000000
1!
1#
1%
1'
b11001001010111 )
b01100100101011 *
0-
#58500000000
0!
0#
b11001001010111 $
0%
0'
b11001001010111 (
#58750000000
1!
1#
1%
1'
b01100100101011 )
b10110010010101 *
1-
#59000000000
0!
0#
b01100100101011 $
0%
0'
b01100100101011 (
#59250000000
1!
1#
1%
1'
b10110010010101 )
b01011001001010 *
0-
#59500000000
0!
0#
b10110010010101 $
0%
0'
b10110010010101 (
#59750000000
1!
1#
1%
1'
b01011001001010 )
b00101100100101 *
#60000000000
0!
0#
b01011001001010 $
0%
0'
b01011001001010 (
#60250000000
1!
1#
1%
1'
b00101100100101 )
b00010110010010 *
#60500000000
0!
0#
b00101100100101 $
0%
0'
b00101100100101 (
#60750000000
1!
1#
1%
1'
b00010110010010 )
b10001011001001 *
1-
#61000000000
0!
0#
b00010110010010 $
0%
0'
b00010110010010 (
#61250000000
1!
1#
1%
1'
b10001011001001 )
b01000101100100 *
0-
#61500000000
0!
0#
b10001011001001 $
0%
0'
b10001011001001 (
#61750000000
1!
1#
1%
1'
b01000101100100 )
b10100010110010 *
1-
#62000000000
0!
0#
b01000101100100 $
0%
0'
b01000101100100 (
#62250000000
1!
1#
1%
1'
b10100010110010 )
b01010001011001 *
0-
#62500000000
0!
0#
b10100010110010 $
0%
0'
b10100010110010 (
#62750000000
1!
1#
1%
1'
b01010001011001 )
b00101000101100 *
#63000000000
0!
0#
b01010001011001 $
0%
0'
b01010001011001 (
#63250000000
1!
1#
1%
1'
b00101000101100 )
b10010100010110 *
1-
#63500000000
0!
0#
b00101000101100 $
0%
0'
b00101000101100 (
#63750000000
1!
1#
1%
1'
b10010100010110 )
b11001010001011 *
#64000000000
0!
0#
b10010100010110 $
0%
0'
b10010100010110 (
#64250000000
1!
1#
1%
1'
b11001010001011 )
b01100101000101 *
0-
#64500000000
0!
0#
b11001010001011 $
0%
0'
b11001010001011 (
#64750000000
1!
1#
1%
1'
b01100101000101 )
b00110010100010 *
#65000000000
0!
0#
b01100101000101 $
0%
0'
b01100101000101 (
#65250000000
1!
1#
1%
1'
b00110010100010 )
b00011001010001 *
#65500000000
0!
0#
b00110010100010 $
0%
0'
b00110010100010 (
#65750000000
1!
1#
1%
1'
b00011001010001 )
b00001100101000 *
#66000000000
0!
0#
b00011001010001 $
0%
0'
b00011001010001 (
#66250000000
1!
1#
1%
1'
b00001100101000 )
b00000110010100 *
#66500000000
0!
0#
b00001100101000 $
0%
0'
b00001100101000 (
#66750000000
1!
1#
1%
1'
b00000110010100 )
b00000011001010 *
#67000000000
0!
0#
b00000110010100 $
0%
0'
b00000110010100 (
#67250000000
1!
1#
1%
1'
b00000011001010 )
b00000001100101 *
#67500000000
0!
0#
b00000011001010 $
0%
0'
b00000011001010 (
#67750000000
1!
1#
1%
1'
b00000001100101 )
b00000000110010 *
#68000000000
0!
0#
b00000001111111 $
0%
0'
b00000001111111 (
#68250000000
1!
1#
1%
1'
b00000000110010 )
b10000000011001 *
1-
#68500000000
0!
0#
0%
0'
#68750000000
1!
1#
1%
1'
b10000000011001 )
b11000000001100 *
#69000000000
0!
0#
b10000000011001 $
0%
0'
b10000000011001 (
#69250000000
1!
1#
1%
1'
b11000000001100 )
b01100000000110 *
0-
#69500000000
0!
0#
b11000000001100 $
0%
0'
b11000000001100 (
#69750000000
1!
1#
1%
1'
b01100000000110 )
b10110000000011 *
1-
#70000000000
0!
0#
b01100000000110 $
0%
0'
b01100000000110 (
#70250000000
1!
1#
1%
1'
b10110000000011 )
b01011000000001 *
0-
#70500000000
0!
0#
b10110000000011 $
0%
0'
b10110000000011 (
#70750000000
1!
1#
1%
1'
b01011000000001 )
b10101100000000 *
1-
#71000000000
0!
0#
b01011000000001 $
0%
0'
b01011000000001 (
#71250000000
1!
1#
1%
1'
b10101100000000 )
b11010110000000 *
#71500000000
0!
0#
b10101100000000 $
0%
0'
b10101100000000 (
#71750000000
1!
1#
1%
1'
b11010110000000 )
b11101011000000 *
#72000000000
0!
0#
b11010110000000 $
0%
0'
b11010110000000 (
#72250000000
1!
1#
1%
1'
b11101011000000 )
b11110101100000 *
#72500000000
0!
0#
b11101011000000 $
0%
0'
b11101011000000 (
#72750000000
1!
1#
1%
1'
b11110101100000 )
b11111010110000 *
#73000000000
0!
0#
b11110101100000 $
0%
0'
b11110101100000 (
#73250000000
1!
1#
1%
1'
b11111010110000 )
b01111101011000 *
0-
#73500000000
0!
0#
b11111010110000 $
0%
0'
b11111010110000 (
#73750000000
1!
1#
1%
1'
b01111101011000 )
b10111110101100 *
1-
#74000000000
0!
0#
b01111101011000 $
0%
0'
b01111101011000 (
#74250000000
1!
1#
1%
1'
b10111110101100 )
b01011111010110 *
0-
#74500000000
0!
0#
b10111110101100 $
0%
0'
b10111110101100 (
#74750000000
1!
1#
1%
1'
b01011111010110 )
b00101111101011 *
#75000000000
0!
0#
b01011111010110 $
0%
0'
b01011111010110 (
#75250000000
1!
1#
1%
1'
b00101111101011 )
b10010111110101 *
1-
#75500000000
0!
0#
b00101111101011 $
0%
0'
b00101111101011 (
#75750000000
1!
1#
1%
1'
b10010111110101 )
b01001011111010 *
0-
#76000000000
0!
0#
b10010111110101 $
0%
0'
b10010111110101 (
#76250000000
1!
1#
1%
1'
b01001011111010 )
b10100101111101 *
1-
#76500000000
0!
0#
b01001011111010 $
0%
0'
b01001011111010 (
#76750000000
1!
1#
1%
1'
b10100101111101 )
b01010010111110 *
0-
#77000000000
0!
0#
b10100101111101 $
0%
0'
b10100101111101 (
#77250000000
1!
1#
1%
1'
b01010010111110 )
b00101001011111 *
#77500000000
0!
0#
b01010010111110 $
0%
0'
b01010010111110 (
#77750000000
1!
1#
1%
1'
b00101001011111 )
b10010100101111 *
1-
#78000000000
0!
0#
b00101001011111 $
0%
0'
b00101001011111 (
#78250000000
1!
1#
1%
1'
b10010100101111 )
b11001010010111 *
#78500000000
0!
0#
b10010100101111 $
0%
0'
b10010100101111 (
#78750000000
1!
1#
1%
1'
b11001010010111 )
b01100101001011 *
0-
#79000000000
0!
0#
b11001010010111 $
0%
0'
b11001010010111 (
#79250000000
1!
1#
1%
1'
b01100101001011 )
b10110010100101 *
1-
#79500000000
0!
0#
b01100101001011 $
0%
0'
b01100101001011 (
#79750000000
1!
1#
1%
1'
b10110010100101 )
b11011001010010 *
#80000000000
0!
0#
b10110010100101 $
0%
0'
b10110010100101 (
#80250000000
1!
1#
1%
1'
b11011001010010 )
b01101100101001 *
0-
#80500000000
0!
0#
b11011001010010 $
0%
0'
b11011001010010 (
#80750000000
1!
1#
1%
1'
b01101100101001 )
b10110110010100 *
1-
#81000000000
0!
0#
b01101100101001 $
0%
0'
b01101100101001 (
#81250000000
1!
1#
1%
1'
b10110110010100 )
b11011011001010 *
#81500000000
0!
0#
b10110110010100 $
0%
0'
b10110110010100 (
#81750000000
1!
1#
1%
1'
b11011011001010 )
b11101101100101 *
#82000000000
0!
0#
b11011011001010 $
0%
0'
b11011011001010 (
#82250000000
1!
1#
1%
1'
b11101101100101 )
b11110110110010 *
#82500000000
0!
0#
b11101101100101 $
0%
0'
b11101101100101 (
#82750000000
1!
1#
1%
1'
b11110110110010 )
b01111011011001 *
0-
#83000000000
0!
0#
b11110110110010 $
0%
0'
b11110110110010 (
#83250000000
1!
1#
1%
1'
b01111011011001 )
b00111101101100 *
#83500000000
0!
0#
b01111011011001 $
0%
0'
b01111011011001 (
#83750000000
1!
1#
1%
1'
b00111101101100 )
b10011110110110 *
1-
#84000000000
0!
0#
b00111101101100 $
0%
0'
b00111101101100 (
#84250000000
1!
1#
1%
1'
b10011110110110 )
b11001111011011 *
#84500000000
0!
0#
b10011110110110 $
0%
0'
b10011110110110 (
#84750000000
1!
1#
1%
1'
b11001111011011 )
b11100111101101 *
#85000000000
0!
0#
b11001111011011 $
0%
0'
b11001111011011 (
#85250000000
1!
1#
1%
1'
b11100111101101 )
b11110011110110 *
#85500000000
0!
0#
b11100111101101 $
0%
0'
b11100111101101 (
#85750000000
1!
1#
1%
1'
b11110011110110 )
b11111001111011 *
#86000000000
0!
0#
b11110011110110 $
0%
0'
b11110011110110 (
#86250000000
1!
1#
1%
1'
b11111001111011 )
b11111100111101 *
#86500000000
0!
0#
b11111001111011 $
0%
0'
b11111001111011 (
#86750000000
1!
1#
1%
1'
b11111100111101 )
b01111110011110 *
0-
#87000000000
0!
0#
b11111100111101 $
0%
0'
b11111100111101 (
#87250000000
1!
1#
1%
1'
b01111110011110 )
b00111111001111 *
#87500000000
0!
0#
b01111110011110 $
0%
0'
b01111110011110 (
#87750000000
1!
1#
1%
1'
b00111111001111 )
b00011111100111 *
#88000000000
0!
0#
b00111111001111 $
0%
0'
b00111111001111 (
#88250000000
1!
1#
1%
1'
b00011111100111 )
b00001111110011 *
#88500000000
0!
0#
b00011111100111 $
0%
0'
b00011111100111 (
#88750000000
1!
1#
1%
1'
b00001111110011 )
b00000111111001 *
#89000000000
0!
0#
b00001111110011 $
0%
0'
b00001111110011 (
#89250000000
1!
1#
1%
1'
b00000111111001 )
b00000011111100 *
#89500000000
0!
0#
b00000111111001 $
0%
0'
b00000111111001 (
#89750000000
1!
1#
1%
1'
b00000011111100 )
b00000001111110 *
#90000000000
0!
0#
b00000011111100 $
0%
0'
b00000011111100 (
#90250000000
1!
1#
1%
1'
b00000001111110 )
b00000000111111 *
#90500000000
0!
0#
b00000001111111 $
0%
0'
b00000001111111 (
#90750000000
1!
1#
1%
1'
b00000000111111 )
b10000000011111 *
1-
#91000000000
0!
0#
0%
0'
#91250000000
1!
1#
1%
1'
b10000000011111 )
b01000000001111 *
0-
#91500000000
0!
0#
b10000000011111 $
0%
0'
b10000000011111 (
#91750000000
1!
1#
1%
1'
b01000000001111 )
b00100000000111 *
#92000000000
0!
0#
b01000000001111 $
0%
0'
b01000000001111 (
#92250000000
1!
1#
1%
1'
b00100000000111 )
b00010000000011 *
#92500000000
0!
0#
b00100000000111 $
0%
0'
b00100000000111 (
#92750000000
1!
1#
1%
1'
b00010000000011 )
b10001000000001 *
1-
#93000000000
0!
0#
b00010000000011 $
0%
0'
b00010000000011 (
#93250000000
1!
1#
1%
1'
b10001000000001 )
b01000100000000 *
0-
#93500000000
0!
0#
b10001000000001 $
0%
0'
b10001000000001 (
#93750000000
1!
1#
1%
1'
b01000100000000 )
b00100010000000 *
