src/pulsegen.vhd
library IEEE;
use IEEE.std_logic_1164.all;
use IEEE.numeric_std.all;


entity pulse_gen is
    port (
        clk : in std_logic;
        output : out std_logic := '0';
        length : in std_logic_vector (13 downto 0);
        delay : in std_logic_vector (13 downto 0);
        send  : in std_logic;
        stop  : in std_logic;
        resp  : out std_logic;
        done : out std_logic
    );
end entity pulse_gen;

architecture rtl of pulse_gen is
    signal length_out : std_logic_vector (13 downto 0) := "00000000000000";
    signal delay_out  : std_logic_vector (13 downto 0):= "00000000000000";
    type SM is (IDLE,SEND_pulse,WAIT_delay,RESPOND);
    signal STATE : SM := IDLE;

begin

    process(clk)
    begin
        if rising_edge(clk) then
            if stop = '1' then
                STATE <= IDLE;
            else
                case STATE is
                    when IDLE =>
                        done <= '0';
                        resp <= '0';
                        if send = '1' then
                            STATE <= SEND_pulse;
                        else
                            STATE <= IDLE;
                        end if;
                    
                    when SEND_pulse =>
                        if length_out >= length then
                            state <= WAIT_delay;
                            length_out <= "00000000000000";
                            output <= '0';
                        else
                            if length_out = std_logic_vector(unsigned(length)-1) then
                                resp <= '1';
                            end if;
                            output <= '1';
                            STATE <= SEND_pulse;    
                            length_out <= std_logic_vector(unsigned(length_out)+1);
                        end if;
                    when WAIT_delay =>
                        resp <= '0';
                        if delay_out = delay  then
                            state <= RESPOND;
                            delay_out <= "00000000000000";
                        else
                            output <= '0';
                            STATE <= WAIT_delay;
                            delay_out <= std_logic_vector(unsigned(delay_out) + 1);
                        end if;
                    when RESPOND =>
                            done <= '1';
                            STATE <= IDLE;
                    
                end case;
            end if;
        end if;
    end process;

end rtl;

src/PRNG.vhd
LIBRARY ieee;
USE ieee.std_logic_1164.ALL;
use IEEE.numeric_std.all;

ENTITY prng IS
  PORT (clk, rst,gen: IN std_logic;
        output: OUT std_logic_vector (13 DOWNTO 0));
END prng;

ARCHITECTURE rtl OF prng IS
  SIGNAL currstate, nextstate: std_logic_vector (13 DOWNTO 0);
  signal min : std_logic_vector(13 downto 0) := "00000001111111";
  signal max : std_logic_vector(13 downto 0) := "11111110000000";

  SIGNAL feedback: std_logic;
BEGIN

  StateReg: PROCESS (clk,Rst)
  BEGIN
    IF (rst = '1') THEN
      currstate <= (0 => '1', OTHERS =>'0');
    ELSIF rising_edge(clk) and gen = '1' THEN
        currstate <= nextstate;  
    END IF;
  END PROCESS;

  process(clk)
  begin
    if(currstate < min) then
      output <= min;
    elsif currstate > max then
      output <= max;
    else
      output <= currstate;
    end if;
  end process;    
      
  
  feedback <= currstate(13) XOR currstate(4) XOR currstate(2) XOR currstate(0);
  nextstate <= feedback & currstate(13 DOWNTO 1);

  end rtl;

src/random_pulse_gen.vhd
LIBRARY ieee;
USE ieee.std_logic_1164.ALL;
use IEEE.numeric_std.all;

entity random_pulse_gen is
    port (
        clk : in std_logic;
        rst : in std_logic;
        send : in std_logic;
        stop : in std_logic;
        pulse : out std_logic;
        done : out std_logic
    );

end entity;

architecture rtl of random_pulse_gen is
signal response: std_logic;
signal word : std_logic_vector(13 downto 0);
signal w_length : std_logic_vector(13 downto 0) := "00000000000000";
signal w_delay : std_logic_vector(13 downto 0) := "00000000000000" ;
signal pulse_gen_out : std_logic;

component prng
port (
    clk, rst,gen: IN std_logic;
    output: OUT std_logic_vector (13 DOWNTO 0)
);
end component;

component pulse_gen 
    port (
        clk : in std_logic;
        output : out std_logic ;
        length : in std_logic_vector (13 downto 0);
        delay : in std_logic_vector (13 downto 0);
        send  : in std_logic;
        stop  : in std_logic;
        resp  : out std_logic;
        done : out std_logic
    );
end component;

signal shift : std_logic := '0';
signal gen : std_logic;
begin
    gen <= response or send;   
    pulse <= not pulse_gen_out;
    prng_inst : prng
        port map (
            clk => clk,
            rst => rst,
            gen => gen,
            output => word
        );
    
    
    process(clk)
    begin
        if response = '1' then
            w_delay <= word;
            w_length <= "00000000000000";
        elsif send = '1' then
            w_length <= word;
            w_delay <= "00000000000000";
        end if;
    end process;

    pulse_gen_inst : pulse_gen
                port map (
                    clk => clk,
                    output => pulse_gen_out,
                    length => w_length,
                    delay => w_delay,
                    send => send,
                    stop => stop,
                    resp => response,
                    done => done
                );
end rtl;

src/random_tb.vhd
library ieee;
use ieee.std_logic_1164.all;
use ieee.numeric_std.all;

entity random_tb is
end random_tb;

architecture tb of random_tb is
    constant CLK_PERIOD : time := 500 ns;
    signal clk :  std_logic:='0';
    signal rst :  std_logic:= '1';
    signal send :  std_logic;
    signal stop :  std_logic;
    signal pulse :  std_logic;
    signal done : std_logic;
    signal wait_r : std_logic;

    component random_pulse_gen  
        port (
            clk : in std_logic;
            rst : in std_logic;
            send : in std_logic;
            stop : in std_logic;
            pulse : out std_logic;
            done : out std_logic           
        );
    end component;

begin
    rpg_inst : random_pulse_gen
        port map (
            clk => clk,
            rst => rst,
            send => send,
            stop => stop,
            pulse => pulse,
            done => done
        );

    clk <= not clk after CLK_PERIOD/2;
    process begin
        rst <= '1';
        wait for 530 ns;
        rst <= '0';
        send <= '1';
        wait for 530 ns;
        send <= '0';
        wait until done = '1';
        send <= '1';
        wait for 530 ns;
        send <= '0';
        wait;
    end process;  
end tb;

src/test.vcd
$date
  Mon May 31 23:30:04 2021
$end
$version
  GHDL v0
$end
$timescale
  1 fs
$end
$scope module standard $end
$upscope $end
$scope module std_logic_1164 $end
$upscope $end
$scope module numeric_std $end
$upscope $end
$scope module random_tb $end
$var reg 1 ! clk $end
$var reg 1 " rst $end
$var reg 1 # send $end
$var reg 1 $ stop $end
$var reg 1 % pulse $end
$var reg 1 & done $end
$var reg 1 ' wait_r $end
$scope module rpg_inst $end
$var reg 1 ( clk $end
$var reg 1 ) rst $end
$var reg 1 * send $end
$var reg 1 + stop $end
$var reg 1 , pulse $end
$var reg 1 - done $end
$var reg 1 . response $end
$var reg 14 / word[13:0] $end
$var reg 14 0 w_length[13:0] $end
$var reg 14 1 w_delay[13:0] $end
$var reg 1 2 pulse_gen_out $end
$var reg 1 3 shift $end
$var reg 1 4 gen $end
$scope module prng_inst $end
$var reg 1 5 clk $end
$var reg 1 6 rst $end
$var reg 1 7 gen $end
$var reg 14 8 output[13:0] $end
$var reg 14 9 currstate[13:0] $end
$var reg 14 : nextstate[13:0] $end
$var reg 14 ; min[13:0] $end
$var reg 14 < max[13:0] $end
$var reg 1 = feedback $end
$upscope $end
$scope module pulse_gen_inst $end
$var reg 1 > clk $end
$var reg 1 ? output $end
$var reg 14 @ length[13:0] $end
$var reg 14 A delay[13:0] $end
$var reg 1 B send $end
$var reg 1 C stop $end
$var reg 1 D resp $end
$var reg 1 E done $end
$var reg 14 F length_out[13:0] $end
$var reg 14 G delay_out[13:0] $end
$comment state is not handled $end
$upscope $end
$upscope $end
$upscope $end
$enddefinitions $end
#0
0!
1"
U#
U$
1%
U&
U'
0(
1)
U*
U+
1,
U-
U.
b00000001111111 /
b00000000000000 0
b00000000000000 1
02
03
U4
05
16
U7
b00000001111111 8
b00000000000001 9
b10000000000000 :
b00000001111111 ;
b11111110000000 <
1=
0>
0?
b00000000000000 @
b00000000000000 A
UB
UC
UD
UE
b00000000000000 F
b00000000000000 G
#250000000
1!
0&
1(
0-
0.
15
1>
0D
0E
#500000000
0!
0(
05
0>
#530000000
0"
1#
0)
1*
14
06
17
1B
#750000000
1!
1(
b00000001111111 0
15
b10000000000000 9
b11000000000000 :
1>
b00000001111111 @
#1000000000
0!
0(
b10000000000000 /
05
b10000000000000 8
0>
#1060000000
0#
0*
04
07
0B
#1250000000
1!
0%
1(
0,
12
15
1>
1?
b00000000000001 F
#1500000000
0!
0(
05
0>
#1750000000
1!
1(
15
1>
b00000000000010 F
#2000000000
0!
0(
05
0>
#2250000000
1!
1(
15
1>
b00000000000011 F
#2500000000
0!
0(
05
0>
#2750000000
1!
1(
15
1>
b00000000000100 F
#3000000000
0!
0(
05
0>
#3250000000
1!
1(
15
1>
b00000000000101 F
#3500000000
0!
0(
05
0>
#3750000000
1!
1(
15
1>
b00000000000110 F
#4000000000
0!
0(
05
0>
#4250000000
1!
1(
15
1>
b00000000000111 F
#4500000000
0!
0(
05
0>
#4750000000
1!
1(
15
1>
b00000000001000 F
#5000000000
0!
0(
05
0>
#5250000000
1!
1(
15
1>
b00000000001001 F
#5500000000
0!
0(
05
0>
#5750000000
1!
1(
15
1>
b00000000001010 F
#6000000000
0!
0(
05
0>
#6250000000
1!
1(
15
1>
b00000000001011 F
#6500000000
0!
0(
05
0>
#6750000000
1!
1(
15
1>
b00000000001100 F
#7000000000
0!
0(
05
0>
#7250000000
1!
1(
15
1>
b00000000001101 F
#7500000000
0!
0(
05
0>
#7750000000
1!
1(
15
1>
b00000000001110 F
#8000000000
0!
0(
05
0>
#8250000000
1!
1(
15
1>
b00000000001111 F
#8500000000
0!
0(
05
0>
#8750000000
1!
1(
15
1>
b00000000010000 F
#9000000000
0!
0(
05
0>
#9250000000
1!
1(
15
1>
b00000000010001 F
#9500000000
0!
0(
05
0>
#9750000000
1!
1(
15
1>
b00000000010010 F
#10000000000
0!
0(
05
0>
#10250000000
1!
1(
15
1>
b00000000010011 F
#10500000000
0!
0(
05
0>
#10750000000
1!
1(
15
1>
b00000000010100 F
#11000000000
0!
0(
05
0>
#11250000000
1!
1(
15
1>
b00000000010101 F
#11500000000
0!
0(
05
0>
#11750000000
1!
1(
15
1>
b00000000010110 F
#12000000000
0!
0(
05
0>
#12250000000
1!
1(
15
1>
b00000000010111 F
#12500000000
0!
0(
05
0>
#12750000000
1!
1(
15
1>
b00000000011000 F
#13000000000
0!
0(
05
0>
#13250000000
1!
1(
15
1>
b00000000011001 F
#13500000000
0!
0(
05
0>
#13750000000
1!
1(
15
1>
b00000000011010 F
#14000000000
0!
0(
05
0>
#14250000000
1!
1(
15
1>
b00000000011011 F
#14500000000
0!
0(
05
0>
#14750000000
1!
1(
15
1>
b00000000011100 F
#15000000000
0!
0(
05
0>
#15250000000
1!
1(
15
1>
b00000000011101 F
#15500000000
0!
0(
05
0>
#15750000000
1!
1(
15
1>
b00000000011110 F
#16000000000
0!
0(
05
0>
#16250000000
1!
1(
15
1>
b00000000011111 F
#16500000000
0!
0(
05
0>
#16750000000
1!
1(
15
1>
b00000000100000 F
#17000000000
0!
0(
05
0>
#17250000000
1!
1(
15
1>
b00000000100001 F
#17500000000
0!
0(
05
0>
#17750000000
1!
1(
15
1>
b00000000100010 F
#18000000000
0!
0(
05
0>
#18250000000
1!
1(
15
1>
b00000000100011 F
#18500000000
0!
0(
05
0>
#18750000000
1!
1(
15
1>
b00000000100100 F
#19000000000
0!
0(
05
0>
#19250000000
1!
1(
15
1>
b00000000100101 F
#19500000000
0!
0(
05
0>
#19750000000
1!
1(
15
1>
b00000000100110 F
#20000000000
0!
0(
05
0>
#20250000000
1!
1(
15
1>
b00000000100111 F
#20500000000
0!
0(
05
0>
#20750000000
1!
1(
15
1>
b00000000101000 F
#21000000000
0!
0(
05
0>
#21250000000
1!
1(
15
1>
b00000000101001 F
#21500000000
0!
0(
05
0>
#21750000000
1!
1(
15
1>
b00000000101010 F
#22000000000
0!
0(
05
0>
#22250000000
1!
1(
15
1>
b00000000101011 F
#22500000000
0!
0(
05
0>
#22750000000
1!
1(
15
1>
b00000000101100 F
#23000000000
0!
0(
05
0>
#23250000000
1!
1(
15
1>
b00000000101101 F
#23500000000
0!
0(
05
0>
#23750000000
1!
1(
15
1>
b00000000101110 F
#24000000000
0!
0(
05
0>
#24250000000
1!
1(
15
1>
b00000000101111 F
#24500000000
0!
0(
05
0>
#24750000000
1!
1(
15
1>
b00000000110000 F
#25000000000
0!
0(
05
0>
#25250000000
1!
1(
15
1>
b00000000110001 F
#25500000000
0!
0(
05
0>
#25750000000
1!
1(
15
1>
b00000000110010 F
#26000000000
0!
0(
05
0>
#26250000000
1!
1(
15
1>
b00000000110011 F
#26500000000
0!
0(
05
0>
#26750000000
1!
1(
15
1>
b00000000110100 F
#27000000000
0!
0(
05
0>
#27250000000
1!
1(
15
1>
b00000000110101 F
#27500000000
0!
0(
05
0>
#27750000000
1!
1(
15
1>
b00000000110110 F
#28000000000
0!
0(
05
0>
#28250000000
1!
1(
15
1>
b00000000110111 F
#28500000000
0!
0(
05
0>
#28750000000
1!
1(
15
1>
b00000000111000 F
#29000000000
0!
0(
05
0>
#29250000000
1!
1(
15
1>
b00000000111001 F
#29500000000
0!
0(
05
0>
#29750000000
1!
1(
15
1>
b00000000111010 F
#30000000000
0!
0(
05
0>
#30250000000
1!
1(
15
1>
b00000000111011 F
#30500000000
0!
0(
05
0>
#30750000000
1!
1(
15
1>
b00000000111100 F
#31000000000
0!
0(
05
0>
#31250000000
1!
1(
15
1>
b00000000111101 F
#31500000000
0!
0(
05
0>
#31750000000
1!
1(
15
1>
b00000000111110 F
#32000000000
0!
0(
05
0>
#32250000000
1!
1(
15
1>
b00000000111111 F
#32500000000
0!
0(
05
0>
#32750000000
1!
1(
15
1>
b00000001000000 F
#33000000000
0!
0(
05
0>
#33250000000
1!
1(
15
1>
b00000001000001 F
#33500000000
0!
0(
05
0>
#33750000000
1!
1(
15
1>
b00000001000010 F
#34000000000
0!
0(
05
0>
#34250000000
1!
1(
15
1>
b00000001000011 F
#34500000000
0!
0(
05
0>
#34750000000
1!
1(
15
1>
b00000001000100 F
#35000000000
0!
0(
05
0>
#35250000000
1!
1(
15
1>
b00000001000101 F
#35500000000
0!
0(
05
0>
#35750000000
1!
1(
15
1>
b00000001000110 F
#36000000000
0!
0(
05
0>
#36250000000
1!
1(
15
1>
b00000001000111 F
#36500000000
0!
0(
05
0>
#36750000000
1!
1(
15
1>
b00000001001000 F
#37000000000
0!
0(
05
0>
#37250000000
1!
1(
15
1>
b00000001001001 F
#37500000000
0!
0(
05
0>
#37750000000
1!
1(
15
1>
b00000001001010 F
#38000000000
0!
0(
05
0>
#38250000000
1!
1(
15
1>
b00000001001011 F
#38500000000
0!
0(
05
0>
#38750000000
1!
1(
15
1>
b00000001001100 F
#39000000000
0!
0(
05
0>
#39250000000
1!
1(
15
1>
b00000001001101 F
#39500000000
0!
0(
05
0>
#39750000000
1!
1(
15
1>
b00000001001110 F
#40000000000
0!
0(
05
0>
#40250000000
1!
1(
15
1>
b00000001001111 F
#40500000000
0!
0(
05
0>
#40750000000
1!
1(
15
1>
b00000001010000 F
#41000000000
0!
0(
05
0>
#41250000000
1!
1(
15
1>
b00000001010001 F
#41500000000
0!
0(
05
0>
#41750000000
1!
1(
15
1>
b00000001010010 F
#42000000000
0!
0(
05
0>
#42250000000
1!
1(
15
1>
b00000001010011 F
#42500000000
0!
0(
05
0>
#42750000000
1!
1(
15
1>
b00000001010100 F
#43000000000
0!
0(
05
0>
#43250000000
1!
1(
15
1>
b00000001010101 F
#43500000000
0!
0(
05
0>
#43750000000
1!
1(
15
1>
b00000001010110 F
#44000000000
0!
0(
05
0>
#44250000000
1!
1(
15
1>
b00000001010111 F
#44500000000
0!
0(
05
0>
#44750000000
1!
1(
15
1>
b00000001011000 F
#45000000000
0!
0(
05
0>
#45250000000
1!
1(
15
1>
b00000001011001 F
#45500000000
0!
0(
05
0>
#45750000000
1!
1(
15
1>
b00000001011010 F
#46000000000
0!
0(
05
0>
#46250000000
1!
1(
15
1>
b00000001011011 F
#46500000000
0!
0(
05
0>
#46750000000
1!
1(
15
1>
b00000001011100 F
#47000000000
0!
0(
05
0>
#47250000000
1!
1(
15
1>
b00000001011101 F
#47500000000
0!
0(
05
0>
#47750000000
1!
1(
15
1>
b00000001011110 F
#48000000000
0!
0(
05
0>
#48250000000
1!
1(
15
1>
b00000001011111 F
#48500000000
0!
0(
05
0>
#48750000000
1!
1(
15
1>
b00000001100000 F
#49000000000
0!
0(
05
0>
#49250000000
1!
1(
15
1>
b00000001100001 F
#49500000000
0!
0(
05
0>
#49750000000
1!
1(
15
1>
b00000001100010 F
#50000000000
0!
0(
05
0>
#50250000000
1!
1(
15
1>
b00000001100011 F
#50500000000
0!
0(
05
0>
#50750000000
1!
1(
15
1>
b00000001100100 F
#51000000000
0!
0(
05
0>
#51250000000
1!
1(
15
1>
b00000001100101 F
#51500000000
0!
0(
05
0>
#51750000000
1!
1(
15
1>
b00000001100110 F
#52000000000
0!
0(
05
0>
#52250000000
1!
1(
15
1>
b00000001100111 F
#52500000000
0!
0(
05
0>
#52750000000
1!
1(
15
1>
b00000001101000 F
#53000000000
0!
0(
05
0>
#53250000000
1!
1(
15
1>
b00000001101001 F
#53500000000
0!
0(
05
0>
#53750000000
1!
1(
15
1>
b00000001101010 F
#54000000000
0!
0(
05
0>
#54250000000
1!
1(
15
1>
b00000001101011 F
#54500000000
0!
0(
05
0>
#54750000000
1!
1(
15
1>
b00000001101100 F
#55000000000
0!
0(
05
0>
#55250000000
1!
1(
15
1>
b00000001101101 F
#55500000000
0!
0(
05
0>
#55750000000
1!
1(
15
1>
b00000001101110 F
#56000000000
0!
0(
05
0>
#56250000000
1!
1(
15
1>
b00000001101111 F
#56500000000
0!
0(
05
0>
#56750000000
1!
1(
15
1>
b00000001110000 F
#57000000000
0!
0(
05
0>
#57250000000
1!
1(
15
1>
b00000001110001 F
#57500000000
0!
0(
05
0>
#57750000000
1!
1(
15
1>
b00000001110010 F
#58000000000
0!
0(
05
0>
#58250000000
1!
1(
15
1>
b00000001110011 F
#58500000000
0!
0(
05
0>
#58750000000
1!
1(
15
1>
b00000001110100 F
#59000000000
0!
0(
05
0>
#59250000000
1!
1(
15
1>
b00000001110101 F
#59500000000
0!
0(
05
0>
#59750000000
1!
1(
15
1>
b00000001110110 F
#60000000000
0!
0(
05
0>
#60250000000
1!
1(
15
1>
b00000001110111 F
#60500000000
0!
0(
05
0>
#60750000000
1!
1(
15
1>
b00000001111000 F
#61000000000
0!
0(
05
0>
#61250000000
1!
1(
15
1>
b00000001111001 F
#61500000000
0!
0(
05
0>
#61750000000
1!
1(
15
1>
b00000001111010 F
#62000000000
0!
0(
05
0>
#62250000000
1!
1(
15
1>
b00000001111011 F
#62500000000
0!
0(
05
0>
#62750000000
1!
1(
15
1>
b00000001111100 F
#63000000000
0!
0(
05
0>
#63250000000
1!
1(
15
1>
b00000001111101 F
#63500000000
0!
0(
05
0>
#63750000000
1!
1(
15
1>
b00000001111110 F
#64000000000
0!
0(
05
0>
#64250000000
1!
1(
1.
14
15
17
1>
1D
b00000001111111 F
#64500000000
0!
0(
b00000000000000 0
b10000000000000 1
05
0>
b00000000000000 @
b10000000000000 A
#64750000000
1!
1%
1(
1,
02
15
b11000000000000 9
b11100000000000 :
1>
0?
b00000000000000 F
#65000000000
0!
0(
b11000000000000 /
05
b11000000000000 8
0>
#65250000000
1!
1(
0.
b11000000000000 1
04
15
07
b11100000000000 9
b11110000000000 :
1>
b11000000000000 A
0D
b00000000000001 G
#65500000000
0!
0(
b11100000000000 /
05
b11100000000000 8
0>
#65750000000
1!
1(
15
1>
b00000000000010 G
#66000000000
0!
0(
05
0>
#66250000000
1!
1(
15
1>
b00000000000011 G
#66500000000
0!
0(
05
0>
#66750000000
1!
1(
15
1>
b00000000000100 G
#67000000000
0!
0(
05
0>
#67250000000
1!
1(
15
1>
b00000000000101 G
#67500000000
0!
0(
05
0>
#67750000000
1!
1(
15
1>
b00000000000110 G
#68000000000
0!
0(
05
0>
#68250000000
1!
1(
15
1>
b00000000000111 G
#68500000000
0!
0(
05
0>
#68750000000
1!
1(
15
1>
b00000000001000 G
#69000000000
0!
0(
05
0>
#69250000000
1!
1(
15
1>
b00000000001001 G
#69500000000
0!
0(
05
0>
#69750000000
1!
1(
15
1>
b00000000001010 G
#70000000000
0!
0(
05
0>
#70250000000
1!
1(
15
1>
b00000000001011 G
#70500000000
0!
0(
05
0>
#70750000000
1!
1(
15
1>
b00000000001100 G
#71000000000
0!
0(
05
0>
#71250000000
1!
1(
15
1>
b00000000001101 G
#71500000000
0!
0(
05
0>
#71750000000
1!
1(
15
1>
b00000000001110 G
#72000000000
0!
0(
05
0>
#72250000000
1!
1(
15
1>
b00000000001111 G
#72500000000
0!
0(
05
0>
#72750000000
1!
1(
15
1>
b00000000010000 G
#73000000000
0!
0(
05
0>
#73250000000
1!
1(
15
1>
b00000000010001 G
#73500000000
0!
0(
05
0>
#73750000000
1!
1(
15
1>
b00000000010010 G
#74000000000
0!
0(
05
0>
#74250000000
1!
1(
15
1>
b00000000010011 G
#74500000000
0!
0(
05
0>
#74750000000
1!
1(
15
1>
b00000000010100 G
#75000000000
0!
0(
05
0>
#75250000000
1!
1(
15
1>
b00000000010101 G
#75500000000
0!
0(
05
0>
#75750000000
1!
1(
15
1>
b00000000010110 G
#76000000000
0!
0(
05
0>
#76250000000
1!
1(
15
1>
b00000000010111 G
#76500000000
0!
0(
05
0>
#76750000000
1!
1(
15
1>
b00000000011000 G
#77000000000
0!
0(
05
0>
#77250000000
1!
1(
15
1>
b00000000011001 G
#77500000000
0!
0(
05
0>
#77750000000
1!
1(
15
1>
b00000000011010 G
#78000000000
0!
0(
05
0>
#78250000000
1!
1(
15
1>
b00000000011011 G
#78500000000
0!
0(
05
0>
#78750000000
1!
1(
15
1>
b00000000011100 G
#79000000000
0!
0(
05
0>
#79250000000
1!
1(
15
1>
b00000000011101 G
#79500000000
0!
0(
05
0>
#79750000000
1!
1(
15
1>
b00000000011110 G
#80000000000
0!
0(
05
0>
#80250000000
1!
1(
15
1>
b00000000011111 G
#80500000000
0!
0(
05
0>
#80750000000
1!
1(
15
1>
b00000000100000 G
#81000000000
0!
0(
05
0>
#81250000000
1!
1(
15
1>
b00000000100001 G
#81500000000
0!
0(
05
0>
#81750000000
1!
1(
15
1>
b00000000100010 G
#82000000000
0!
0(
05
0>
#82250000000
1!
1(
15
1>
b00000000100011 G
#82500000000
0!
0(
05
0>
#82750000000
1!
1(
15
1>
b00000000100100 G
#83000000000
0!
0(
05
0>
#83250000000
1!
1(
15
1>
b00000000100101 G
#83500000000
0!
0(
05
0>
#83750000000
1!
1(
15
1>
b00000000100110 G
#84000000000
0!
0(
05
0>
#84250000000
1!
1(
15
1>
b00000000100111 G
#84500000000
0!
0(
05
0>
#84750000000
1!
1(
15
1>
b00000000101000 G
#85000000000
0!
0(
05
0>
#85250000000
1!
1(
15
1>
b00000000101001 G
#85500000000
0!
0(
05
0>
#85750000000
1!
1(
15
1>
b00000000101010 G
#86000000000
0!
0(
05
0>
#86250000000
1!
1(
15
1>
b00000000101011 G
#86500000000
0!
0(
05
0>
#86750000000
1!
1(
15
1>
b00000000101100 G
#87000000000
0!
0(
05
0>
#87250000000
1!
1(
15
1>
b00000000101101 G
#87500000000
0!
0(
05
0>
#87750000000
1!
1(
15
1>
b00000000101110 G
#88000000000
0!
0(
05
0>
#88250000000
1!
1(
15
1>
b00000000101111 G
#88500000000
0!
0(
05
0>
#88750000000
1!
1(
15
1>
b00000000110000 G
#89000000000
0!
0(
05
0>
#89250000000
1!
1(
15
1>
b00000000110001 G
#89500000000
0!
0(
05
0>
#89750000000
1!
1(
15
1>
b00000000110010 G
#90000000000
0!
0(
05
0>
#90250000000
1!
1(
15
1>
b00000000110011 G
#90500000000
0!
0(
05
0>
#90750000000
1!
1(
15
1>
b00000000110100 G
#91000000000
0!
0(
05
0>
#91250000000
1!
1(
15
1>
b00000000110101 G
#91500000000
0!
0(
05
0>
#91750000000
1!
1(
15
1>
b00000000110110 G
#92000000000
0!
0(
05
0>
#92250000000
1!
1(
15
1>
b00000000110111 G
#92500000000
0!
0(
05
0>
#92750000000
1!
1(
15
1>
b00000000111000 G
#93000000000
0!
0(
05
0>
#93250000000
1!
1(
15
1>
b00000000111001 G
#93500000000
0!
0(
05
0>
#93750000000
1!
1(
15
1>
b00000000111010 G
#94000000000
0!
0(
05
0>
#94250000000
1!
1(
15
1>
b00000000111011 G
#94500000000
0!
0(
05
0>
#94750000000
1!
1(
15
1>
b00000000111100 G
#95000000000
0!
0(
05
0>
#95250000000
1!
1(
15
1>
b00000000111101 G
#95500000000
0!
0(
05
0>
#95750000000
1!
1(
15
1>
b00000000111110 G
#96000000000
0!
0(
05
0>
#96250000000
1!
1(
15
1>
b00000000111111 G
#96500000000
0!
0(
05
0>
#96750000000
1!
1(
15
1>
b00000001000000 G
#97000000000
0!
0(
05
0>
#97250000000
1!
1(
15
1>
b00000001000001 G
#97500000000
0!
0(
05
0>
#97750000000
1!
1(
15
1>
b00000001000010 G
#98000000000
0!
0(
05
0>
#98250000000
1!
1(
15
1>
b00000001000011 G
#98500000000
0!
0(
05
0>
#98750000000
1!
1(
15
1>
b00000001000100 G
#99000000000
0!
0(
05
0>
#99250000000
1!
1(
15
1>
b00000001000101 G
#99500000000
0!
0(
05
0>
#99750000000
1!
1(
15
1>
b00000001000110 G
#100000000000
0!
0(
05
0>
#100250000000
1!
1(
15
1>
b00000001000111 G
#100500000000
0!
0(
05
0>
#100750000000
1!
1(
15
1>
b00000001001000 G
#101000000000
0!
0(
05
0>
#101250000000
1!
1(
15
1>
b00000001001001 G
#101500000000
0!
0(
05
0>
#101750000000
1!
1(
15
1>
b00000001001010 G
#102000000000
0!
0(
05
0>
#102250000000
1!
1(
15
1>
b00000001001011 G
#102500000000
0!
0(
05
0>
#102750000000
1!
1(
15
1>
b00000001001100 G
#103000000000
0!
0(
05
0>
#103250000000
1!
1(
15
1>
b00000001001101 G
#103500000000
0!
0(
05
0>
#103750000000
1!
1(
15
1>
b00000001001110 G
#104000000000
0!
0(
05
0>
#104250000000
1!
1(
15
1>
b00000001001111 G
#104500000000
0!
0(
05
0>
#104750000000
1!
1(
15
1>
b00000001010000 G
#105000000000
0!
0(
05
0>
#105250000000
1!
1(
15
1>
b00000001010001 G
#105500000000
0!
0(
05
0>
#105750000000
1!
1(
15
1>
b00000001010010 G
#106000000000
0!
0(
05
0>
#106250000000
1!
1(
15
1>
b00000001010011 G
#106500000000
0!
0(
05
0>
#106750000000
1!
1(
15
1>
b00000001010100 G
#107000000000
0!
0(
05
0>
#107250000000
1!
1(
15
1>
b00000001010101 G
#107500000000
0!
0(
05
0>
#107750000000
1!
1(
15
1>
b00000001010110 G
#108000000000
0!
0(
05
0>
#108250000000
1!
1(
15
1>
b00000001010111 G
#108500000000
0!
0(
05
0>
#108750000000
1!
1(
15
1>
b00000001011000 G
#109000000000
0!
0(
05
0>
#109250000000
1!
1(
15
1>
b00000001011001 G
#109500000000
0!
0(
05
0>
#109750000000
1!
1(
15
1>
b00000001011010 G
#110000000000
0!
0(
05
0>
#110250000000
1!
1(
15
1>
b00000001011011 G
#110500000000
0!
0(
05
0>
#110750000000
1!
1(
15
1>
b00000001011100 G
#111000000000
0!
0(
05
0>
#111250000000
1!
1(
15
1>
b00000001011101 G
#111500000000
0!
0(
05
0>
#111750000000
1!
1(
15
1>
b00000001011110 G
#112000000000
0!
0(
05
0>
#112250000000
1!
1(
15
1>
b00000001011111 G
#112500000000
0!
0(
05
0>
#112750000000
1!
1(
15
1>
b00000001100000 G
#113000000000
0!
0(
05
0>
#113250000000
1!
1(
15
1>
b00000001100001 G
#113500000000
0!
0(
05
0>
#113750000000
1!
1(
15
1>
b00000001100010 G
#114000000000
0!
0(
05
0>
#114250000000
1!
1(
15
1>
b00000001100011 G
#114500000000
0!
0(
05
0>
#114750000000
1!
1(
15
1>
b00000001100100 G
#115000000000
0!
0(
05
0>
#115250000000
1!
1(
15
1>
b00000001100101 G
#115500000000
0!
0(
05
0>
#115750000000
1!
1(
15
1>
b00000001100110 G
#116000000000
0!
0(
05
0>
#116250000000
1!
1(
15
1>
b00000001100111 G
#116500000000
0!
0(
05
0>
#116750000000
1!
1(
15
1>
b00000001101000 G
#117000000000
0!
0(
05
0>
#117250000000
1!
1(
15
1>
b00000001101001 G
#117500000000
0!
0(
05
0>
#117750000000
1!
1(
15
1>
b00000001101010 G
#118000000000
0!
0(
05
0>
#118250000000
1!
1(
15
1>
b00000001101011 G
#118500000000
0!
0(
05
0>
#118750000000
1!
1(
15
1>
b00000001101100 G
#119000000000
0!
0(
05
0>
#119250000000
1!
1(
15
1>
b00000001101101 G
#119500000000
0!
0(
05
0>
#119750000000
1!
1(
15
1>
b00000001101110 G
#120000000000
0!
0(
05
0>
#120250000000
1!
1(
15
1>
b00000001101111 G
#120500000000
0!
0(
05
0>
#120750000000
1!
1(
15
1>
b00000001110000 G
#121000000000
0!
0(
05
0>
#121250000000
1!
1(
15
1>
b00000001110001 G
#121500000000
0!
0(
05
0>
#121750000000
1!
1(
15
1>
b00000001110010 G
#122000000000
0!
0(
05
0>
#122250000000
1!
1(
15
1>
b00000001110011 G
#122500000000
0!
0(
05
0>
#122750000000
1!
1(
15
1>
b00000001110100 G
#123000000000
0!
0(
05
0>
#123250000000
1!
1(
15
1>
b00000001110101 G
#123500000000
0!
0(
05
0>
#123750000000
1!
1(
15
1>
b00000001110110 G
#124000000000
0!
0(
05
0>
#124250000000
1!
1(
15
1>
b00000001110111 G
#124500000000
0!
0(
05
0>
#124750000000
1!
1(
15
1>
b00000001111000 G
#125000000000
0!
0(
05
0>
#125250000000
1!
1(
15
1>
b00000001111001 G
#125500000000
0!
0(
05
0>
#125750000000
1!
1(
15
1>
b00000001111010 G
#126000000000
0!
0(
05
0>
#126250000000
1!
1(
15
1>
b00000001111011 G
#126500000000
0!
0(
05
0>
#126750000000
1!
1(
15
1>
b00000001111100 G
#127000000000
0!
0(
05
0>
#127250000000
1!
1(
15
1>
b00000001111101 G
#127500000000
0!
0(
05
0>
#127750000000
1!
1(
15
1>
b00000001111110 G
#128000000000
0!
0(
05
0>
#128250000000
1!
1(
15
1>
b00000001111111 G
#128500000000
0!
0(
05
0>
#128750000000
1!
1(
15
1>
b00000010000000 G
#129000000000
0!
0(
05
0>
#129250000000
1!
1(
15
1>
b00000010000001 G
#129500000000
0!
0(
05
0>
